py_adapter/__init__.py
py_adapter/_schema.py
py_adapter/py.typed
py_adapter/plugin/__init__.py
py_adapter/plugin/_avro.py
py_adapter/plugin/_csv.py
py_adapter/plugin/_json.py
py_adapter-0.4.3.dist-info/LICENSE
py_adapter-0.4.3.dist-info/LICENSE_HEADER.txt
py_adapter-0.4.3.dist-info/METADATA
py_adapter-0.4.3.dist-info/WHEEL
py_adapter-0.4.3.dist-info/top_level.txt
py_adapter-0.4.3.dist-info/RECORD
