Metadata-Version: 2.1
Name: py-adapter
Version: 0.4.3
Summary: Round-trip serialization/deserialization of any Python object to/from any serialization format including Avro and JSON.
Author-email: "J.P. Morgan Chase & Co." <open_source@jpmorgan.com>
License: Apache License
Project-URL: Homepage, https://github.com/jpmorganchase/py-adapter
Project-URL: Bug Tracker, https://github.com/jpmorganchase/py-adapter/issues
Project-URL: Documentation, https://py-adapter.readthedocs.io
Project-URL: Download, https://pypi.python.org/pypi/py-adapter
Project-URL: Source Code, https://github.com/jpmorganchase/py-adapter
Keywords: adapter,avro,dataclasses,deserialization,json,pydantic,serialization
Classifier: Development Status :: 5 - Production/Stable
Classifier: License :: OSI Approved :: Apache Software License
Classifier: Operating System :: OS Independent
Classifier: Programming Language :: Python :: 3
Classifier: Typing :: Typed
Requires-Python: >=3.9
License-File: LICENSE
License-File: LICENSE_HEADER.txt
Requires-Dist: avro ~=1.11
Requires-Dist: fastavro ~=1.8
Requires-Dist: memoization ~=0.4
Requires-Dist: more-itertools ~=10.0
Requires-Dist: orjson ~=3.0
Requires-Dist: pluggy ~=1.3
Requires-Dist: py-avro-schema ~=3.0
Requires-Dist: python-dateutil ~=2.8
Provides-Extra: docs
Requires-Dist: sphinx ; extra == 'docs'
Requires-Dist: sphinx-rtd-theme ; extra == 'docs'
Provides-Extra: linting
Requires-Dist: black ; extra == 'linting'
Requires-Dist: flake8 ; extra == 'linting'
Requires-Dist: interrogate ; extra == 'linting'
Requires-Dist: isort ; extra == 'linting'
Requires-Dist: mypy ; extra == 'linting'
Requires-Dist: pre-commit ; extra == 'linting'
Provides-Extra: testing
Requires-Dist: pytest ; extra == 'testing'
Requires-Dist: pytest-cov ; extra == 'testing'
Requires-Dist: pytest-mock ; extra == 'testing'
